{
	"name": "pipeline1",
	"properties": {
		"activities": [
			{
				"name": "Copy Data1",
				"type": "Copy",
				"dependsOn": [],
				"policy": {
					"timeout": "7.00:00:00",
					"retry": 0,
					"retryIntervalInSeconds": 30,
					"secureOutput": false,
					"secureInput": false
				},
				"userProperties": [],
				"typeProperties": {
					"source": {
						"type": "RelationalSource",
						"query": "?RegionID=1"
					},
					"sink": {
						"type": "BlobSink"
					},
					"enableStaging": false
				},
				"inputs": [
					{
						"referenceName": "ODataResource1",
						"type": "DatasetReference"
					}
				],
				"outputs": [
					{
						"referenceName": "AzureBlob1",
						"type": "DatasetReference"
					}
				]
			}
		],
		"annotations": []
	}
}